{
  "icon": {
    "type": "spells_and_shields:advanced",
    "height": 16,
    "icon": "minecraft:textures/entity/ghast/ghast_shooting.png",
    "textureHeight": 32,
    "textureWidth": 64,
    "u": 16,
    "v": 16,
    "width": 16
  },
  "mana_cost": 0.0,
  "spell_actions": [],
  "title": {
    "translate": "spell.spells_and_shields.ghast"
  },
  "tooltip": [
    {
      "translate": "spell.spells_and_shields.ghast.desc"
    },
    {
      "color": "red",
      "italic": true,
      "text": "In Development"
    }
  ],
  "variables": []
}