{
  "events": [],
  "icon": {
    "type": "spells_and_shields:default",
    "texture": "spells_and_shields:textures/spell/leap.png"
  },
  "mana_cost": 5.0,
  "parameters": [
    {
      "type": "spells_and_shields:double",
      "value": 2.5,
      "var/name": "speed"
    }
  ],
  "spell_actions": [
    {
      "type": "spells_and_shields:simple_mana_check",
      "activation": "active"
    },
    {
      "type": "spells_and_shields:reset_fall_distance",
      "activation": "active",
      "ts/targets": "owner"
    },
    {
      "type": "spells_and_shields:get_entity_position_direction",
      "activation": "active",
      "t/source": "owner",
      "td/position": "",
      "var/direction": "look",
      "var/motion": ""
    },
    {
      "type": "spells_and_shields:put_vec3",
      "activation": "active",
      "d/vec3/source": "<< (normalize(look + vec3(0, -get_y(look), 0))) * speed >>",
      "var/result": "direction"
    },
    {
      "type": "spells_and_shields:set_motion",
      "activation": "active",
      "d/vec3/motion": "<< vec3(get_x(direction), max(0.5, get_y(look) + 0.5), get_z(direction)) >>",
      "ts/targets": "owner"
    },
    {
      "type": "spells_and_shields:spawn_particles",
      "activation": "active",
      "d/double/spread": 0.1,
      "d/int/count": 4,
      "particle": {
        "type": "minecraft:poof"
      },
      "ts/targets": "owner"
    },
    {
      "type": "spells_and_shields:play_sound",
      "activation": "active",
      "d/double/pitch": 1.0,
      "d/double/volume": 1.0,
      "sound_event": "minecraft:entity.ender_dragon.flap",
      "ts/targets": "owner"
    }
  ],
  "title": {
    "translate": "spell.spells_and_shields.leap"
  },
  "tooltip": [
    {
      "translate": "spell.spells_and_shields.leap.desc"
    }
  ]
}